[{"id":"13967868","pillar":"industrial-manufacturing","keyword":"equipment shipping calculator","origin":{"date":"10/9/19","city":"BENTONVILLE","state":"AR","country":"USA"},"destination":{"date":"10/11/19","city":"ASHLAND","state":"OH","country":"USA"},"value":5600,"description":"Equipment Axle bound to pallets","height":22,"itemCondition":"\tNew","length":96,"packaging":"","quantity":1,"weight":1564,"width":48,"carrier":{"type":"LTL","name":"Estes Express","image":15145},"price":476.14,"premium":19.59,"additionalServices":"Protect from freezing","freightClass":""},{"id":"14037762","pillar":"industrial-manufacturing","keyword":"equipment shipping calculator","origin":{"date":"2/5/20","city":"SAN JOSE","state":"CA","country":"USA"},"destination":{"date":"2/14/20","city":"PEACHTREE CORNERS","state":"GA","country":"USA"},"value":42500,"description":"Electronic Test Equipment #1","height":28,"itemCondition":"New","length":42,"packaging":"","quantity":1,"weight":300,"width":42,"carrier":{"type":"LTL","name":"ABF Freight System","image":15662},"price":680.4,"premium":297.5,"additionalServices":"Protect from freezing","freightClass":""},{"id":"14037762","pillar":"industrial-manufacturing","keyword":"equipment shipping calculator","origin":{"date":"2/5/20","city":"SAN JOSE","state":"CA","country":"USA"},"destination":{"date":"2/14/20","city":"PEACHTREE CORNERS","state":"GA","country":"USA"},"value":42500,"description":"Electronic Test Equipment #2","height":28,"itemCondition":"New","length":42,"packaging":"","quantity":1,"weight":300,"width":42,"carrier":{"type":"LTL","name":"ABF Freight System","image":15662},"price":680.4,"premium":297.5,"additionalServices":"Protect from freezing","freightClass":""},{"id":"14068990","pillar":"industrial-manufacturing","keyword":"equipment shipping calculator","origin":{"date":"3/25/20","city":"FOND DU LAC","state":"WI","country":"USA"},"destination":{"date":"3/27/20","city":"JAMESTOWN","state":"ND","country":"USA"},"value":2000,"description":"rotor for haybuster equipment","height":24,"itemCondition":"Used","length":48,"packaging":"","quantity":1,"weight":1100,"width":48,"carrier":{"type":"LTL","name":"Midwest Motor Express","image":152266},"price":236.59,"premium":10.5,"additionalServices":"Protect from freezing","freightClass":""},{"id":"14004642","pillar":"industrial-manufacturing","keyword":"equipment shipping calculator","origin":{"date":"12/9/19","city":"WHITMAN","state":"MA","country":"USA"},"destination":{"date":"12/13/19","city":"BAR HARBOR","state":"ME","country":"USA"},"value":1000,"description":"Equipment parts","height":10,"itemCondition":"New","length":14,"packaging":"","quantity":1,"weight":90,"width":14,"carrier":{"type":"LTL","name":"R & L Carriers","image":15252},"price":154.65,"premium":0,"additionalServices":"Protect from freezing","freightClass":""},{"id":"14073092","pillar":"industrial-manufacturing","keyword":"equipment shipping calculator","origin":{"date":"4/1/20","city":"SEBREE","state":"KY","country":"USA"},"destination":{"date":"4/3/20","city":"PANTEGO","state":"NC","country":"USA"},"value":0,"description":"Non-Hazard Electrolyzed Water, Tote Tank","height":48,"itemCondition":"New","length":48,"packaging":"","quantity":1,"weight":2390,"width":48,"carrier":{"type":"LTL","name":"SAIA","image":15259},"price":370.14,"premium":0,"additionalServices":"Protect from freezing","freightClass":""}]