[{"id":"14154752","pillar":"industrial-manufacturing","keyword":"led-sign","origin":{"city":"OAKDALE","state":"CA","country":"USA"},"destination":{"city":"PARAGOULD","state":"AR","country":"USA"},"value":100,"description":"LED Sign","height":59,"itemCondition":"New","length":104,"packaging":"Crates","quantity":1,"weight":475,"width":16,"carrier":{"type":"LTL","name":"Estes","image":"15145"},"price":534,"premium":200,"additionalServices":"Protect from freezing","freightClass":"Class 400"},{"id":"14229920","pillar":"industrial-manufacturing","keyword":"led-sign","origin":{"city":"MANKATO","state":"MN","country":"USA"},"destination":{"city":"LANSDALE","state":"PA","country":"USA"},"value":800,"description":"New LED sign tubes","height":12,"itemCondition":"New","length":120,"packaging":"Boxes","quantity":1,"weight":58,"width":5,"carrier":{"type":"LTL","name":"Estes","image":"15145"},"price":534,"premium":200,"additionalServices":"Protect from freezing","freightClass":"Class 400"},{"id":"14241864","pillar":"industrial-manufacturing","keyword":"led-sign","origin":{"city":"CORVALLIS","state":"OR","country":"USA"},"destination":{"city":"DETROIT","state":"MI","country":"USA"},"value":1033,"description":"LED sign in a box. The box is not stackable or should be bended. Item is considered fragile.","height":8,"itemCondition":"New","length":74,"packaging":"Skids","quantity":1,"weight":30,"width":48,"carrier":{"type":"LTL","name":"Estes","image":"15145"},"price":534,"premium":200,"additionalServices":"Protect from freezing","freightClass":"Class 400"},{"id":"14283438","pillar":"industrial-manufacturing","keyword":"led-sign","origin":{"city":"ROSEMEAD","state":"CA","country":"USA"},"destination":{"city":"RIPLEY","state":"MS","country":"USA"},"value":2000,"description":"Led sign crated","height":30,"itemCondition":"New","length":107,"packaging":"Pallet","quantity":1,"weight":240,"width":37,"carrier":{"type":"LTL","name":"Estes","image":"15145"},"price":534,"premium":200,"additionalServices":"Protect from freezing","freightClass":"Class 400"}]