[{"id":"13646848","pillar":"industrial-manufacturing","keyword":"pickup","origin":{"city":"COLUMBIA","state":"TN","country":"USA"},"destination":{"city":"NEWFIELD","state":"NY","country":"USA"},"value":0,"description":"1992-Ford-F-150 Pickup bed","height":36,"itemCondition":"","length":88,"packaging":"Pallet","quantity":1,"weight":390,"width":73,"carrier":{"type":"LTL","name":"Estes","image":"15145"},"price":534,"premium":200,"additionalServices":"Protect from freezing","freightClass":"Class 400"},{"id":"13653338","pillar":"industrial-manufacturing","keyword":"pickup","origin":{"city":"WASHINGTON","state":"UT","country":"USA"},"destination":{"city":"TONAWANDA","state":"NY","country":"USA"},"value":0,"description":"2005 - Ford - F-250SD Pickup Box","height":36,"itemCondition":"","length":77,"packaging":"Pallet","quantity":1,"weight":380,"width":63,"carrier":{"type":"LTL","name":"Estes","image":"15145"},"price":534,"premium":200,"additionalServices":"Protect from freezing","freightClass":"Class 400"},{"id":"13703090","pillar":"industrial-manufacturing","keyword":"pickup","origin":{"city":"HOUSTON","state":"TX","country":"USA"},"destination":{"city":"JERSEY SHORE","state":"PA","country":"USA"},"value":0,"description":"2002 - ford - f-250sd Pickup Bed (SRW), 6' 9\" box Black","height":36,"itemCondition":"","length":88,"packaging":"Pallet","quantity":1,"weight":300,"width":73,"carrier":{"type":"LTL","name":"Estes","image":"15145"},"price":534,"premium":200,"additionalServices":"Protect from freezing","freightClass":"Class 400"},{"id":"13903546","pillar":"industrial-manufacturing","keyword":"pickup","origin":{"city":"THOMASVILLE","state":"NC","country":"USA"},"destination":{"city":"OLTON","state":"TX","country":"USA"},"value":150,"description":"1996 Nissan Pickup   Engine Assembly","height":38,"itemCondition":"Used","length":40,"packaging":"Pallet","quantity":1,"weight":150,"width":40,"carrier":{"type":"LTL","name":"Estes","image":"15145"},"price":534,"premium":200,"additionalServices":"Protect from freezing","freightClass":"Class 400"},{"id":"14077418","pillar":"industrial-manufacturing","keyword":"pickup","origin":{"city":"SAN ANTONIO","state":"TX","country":"USA"},"destination":{"city":"TOMS RIVER","state":"NJ","country":"USA"},"value":0,"description":"EQUIPMENT PICKUP DETAILS  2015 Mi-T-M CW-3004-4SGH Pressure Washer 3,000  Serial #10831558","height":26,"itemCondition":"Used","length":45,"packaging":"Pallet","quantity":1,"weight":240,"width":28,"carrier":{"type":"LTL","name":"Estes","image":"15145"},"price":534,"premium":200,"additionalServices":"Protect from freezing","freightClass":"Class 400"}]