[{"id":"13571444","pillar":"industrial-manufacturing","keyword":"incinerating-toilet","origin":{"city":"BROOMFIELD","state":"CO","country":"USA"},"destination":{"city":"NORTH LITTLE ROCK","state":"AR","country":"USA"},"value":0,"description":"Incinerating Toilet","height":40,"itemCondition":"","length":40,"packaging":"Pallet","quantity":1,"weight":225,"width":40,"carrier":{"type":"LTL","name":"Estes","image":"15145"},"price":534,"premium":200,"additionalServices":"Protect from freezing","freightClass":"Class 400"},{"id":"13577944","pillar":"industrial-manufacturing","keyword":"incinerating-toilet","origin":{"city":"DE BEQUE","state":"CO","country":"USA"},"destination":{"city":"NORTH LITTLE ROCK","state":"AR","country":"USA"},"value":0,"description":"Incinerating Toilet","height":40,"itemCondition":"","length":40,"packaging":"Pallet","quantity":1,"weight":247,"width":40,"carrier":{"type":"LTL","name":"Estes","image":"15145"},"price":534,"premium":200,"additionalServices":"Protect from freezing","freightClass":"Class 400"},{"id":"13578252","pillar":"industrial-manufacturing","keyword":"incinerating-toilet","origin":{"city":"NORTH LITTLE ROCK","state":"AR","country":"USA"},"destination":{"city":"BELVIDERE","state":"IL","country":"USA"},"value":0,"description":"Incinerating Toilet","height":40,"itemCondition":"","length":48,"packaging":"Pallet","quantity":1,"weight":278,"width":40,"carrier":{"type":"LTL","name":"Estes","image":"15145"},"price":534,"premium":200,"additionalServices":"Protect from freezing","freightClass":"Class 400"},{"id":"13579142","pillar":"industrial-manufacturing","keyword":"incinerating-toilet","origin":{"city":"NORTH LITTLE ROCK","state":"AR","country":"USA"},"destination":{"city":"BROOMFIELD","state":"CO","country":"USA"},"value":0,"description":"Incinerating Toilet","height":30,"itemCondition":"","length":48,"packaging":"Pallet","quantity":1,"weight":227,"width":40,"carrier":{"type":"LTL","name":"Estes","image":"15145"},"price":534,"premium":200,"additionalServices":"Protect from freezing","freightClass":"Class 400"},{"id":"13602908","pillar":"industrial-manufacturing","keyword":"incinerating-toilet","origin":{"city":"DATIL","state":"NM","country":"USA"},"destination":{"city":"NORTH LITTLE ROCK","state":"AR","country":"USA"},"value":0,"description":"Incinerating Toilet","height":30,"itemCondition":"","length":40,"packaging":"Pallet","quantity":1,"weight":219,"width":40,"carrier":{"type":"LTL","name":"Estes","image":"15145"},"price":534,"premium":200,"additionalServices":"Protect from freezing","freightClass":"Class 400"},{"id":"13617070","pillar":"industrial-manufacturing","keyword":"incinerating-toilet","origin":{"city":"NORTH LITTLE ROCK","state":"AR","country":"USA"},"destination":{"city":"OSHKOSH","state":"WI","country":"USA"},"value":0,"description":"Incinerating Toilet","height":40,"itemCondition":"","length":48,"packaging":"Pallet","quantity":1,"weight":229,"width":40,"carrier":{"type":"LTL","name":"Estes","image":"15145"},"price":534,"premium":200,"additionalServices":"Protect from freezing","freightClass":"Class 400"},{"id":"13628190","pillar":"industrial-manufacturing","keyword":"incinerating-toilet","origin":{"city":"WINCHESTER","state":"VA","country":"USA"},"destination":{"city":"NORTH LITTLE ROCK","state":"AR","country":"USA"},"value":0,"description":"Incinerating Toilet","height":35,"itemCondition":"","length":40,"packaging":"Pallet","quantity":1,"weight":246,"width":35,"carrier":{"type":"LTL","name":"Estes","image":"15145"},"price":534,"premium":200,"additionalServices":"Protect from freezing","freightClass":"Class 400"},{"id":"13646020","pillar":"industrial-manufacturing","keyword":"incinerating-toilet","origin":{"city":"NORTH LITTLE ROCK","state":"AR","country":"USA"},"destination":{"city":"WINCHESTER","state":"VA","country":"USA"},"value":0,"description":"Incinerating Toilet","height":36,"itemCondition":"","length":40,"packaging":"Pallet","quantity":1,"weight":234,"width":40,"carrier":{"type":"LTL","name":"Estes","image":"15145"},"price":534,"premium":200,"additionalServices":"Protect from freezing","freightClass":"Class 400"},{"id":"13654424","pillar":"industrial-manufacturing","keyword":"incinerating-toilet","origin":{"city":"NORTH LITTLE ROCK","state":"AR","country":"USA"},"destination":{"city":"WILMINGTON","state":"MA","country":"USA"},"value":0,"description":"Incinerating Toilet","height":30,"itemCondition":"","length":48,"packaging":"Pallet","quantity":1,"weight":236,"width":35,"carrier":{"type":"LTL","name":"Estes","image":"15145"},"price":534,"premium":200,"additionalServices":"Protect from freezing","freightClass":"Class 400"},{"id":"13704862","pillar":"industrial-manufacturing","keyword":"incinerating-toilet","origin":{"city":"SPRINGDALE","state":"PA","country":"USA"},"destination":{"city":"NORTH LITTLE ROCK","state":"AR","country":"USA"},"value":0,"description":"Incinerating Toilet","height":30,"itemCondition":"","length":48,"packaging":"Pallet","quantity":1,"weight":235,"width":40,"carrier":{"type":"LTL","name":"Estes","image":"15145"},"price":534,"premium":200,"additionalServices":"Protect from freezing","freightClass":"Class 400"},{"id":"13715684","pillar":"industrial-manufacturing","keyword":"incinerating-toilet","origin":{"city":"FREDERICKSBURG","state":"VA","country":"USA"},"destination":{"city":"NORTH LITTLE ROCK","state":"AR","country":"USA"},"value":0,"description":"Incinerating Toilet","height":35,"itemCondition":"","length":48,"packaging":"Pallet","quantity":1,"weight":236,"width":40,"carrier":{"type":"LTL","name":"Estes","image":"15145"},"price":534,"premium":200,"additionalServices":"Protect from freezing","freightClass":"Class 400"},{"id":"13806994","pillar":"industrial-manufacturing","keyword":"incinerating-toilet","origin":{"city":"NORTH LITTLE ROCK","state":"AR","country":"USA"},"destination":{"city":"SAN ANTONIO","state":"TX","country":"USA"},"value":0,"description":"Incinerating Toilet","height":40,"itemCondition":"","length":48,"packaging":"Pallet","quantity":1,"weight":236,"width":40,"carrier":{"type":"LTL","name":"Estes","image":"15145"},"price":534,"premium":200,"additionalServices":"Protect from freezing","freightClass":"Class 400"},{"id":"13849188","pillar":"industrial-manufacturing","keyword":"incinerating-toilet","origin":{"city":"FLAGSTAFF","state":"AZ","country":"USA"},"destination":{"city":"NORTH LITTLE ROCK","state":"AR","country":"USA"},"value":0,"description":"Incinerating toilet","height":30,"itemCondition":"New","length":48,"packaging":"Pallet","quantity":1,"weight":235,"width":40,"carrier":{"type":"LTL","name":"Estes","image":"15145"},"price":534,"premium":200,"additionalServices":"Protect from freezing","freightClass":"Class 400"},{"id":"13853126","pillar":"industrial-manufacturing","keyword":"incinerating-toilet","origin":{"city":"NORTH LITTLE ROCK","state":"AR","country":"USA"},"destination":{"city":"SAN ANTONIO","state":"TX","country":"USA"},"value":0,"description":"Incinerating Toilet","height":40,"itemCondition":"New","length":48,"packaging":"Pallet","quantity":1,"weight":234,"width":40,"carrier":{"type":"LTL","name":"Estes","image":"15145"},"price":534,"premium":200,"additionalServices":"Protect from freezing","freightClass":"Class 400"}]