[{"id":"13381987","pillar":"industrial-manufacturing","keyword":"compressor","origin":{"city":"HAMILTON","state":"OH","country":"USA"},"destination":{"city":"SAN DIEGO","state":"CA","country":"USA"},"value":0,"description":"3 refrigeration compressors","height":36,"itemCondition":"","length":80,"packaging":"Pallet","quantity":1,"weight":1125,"width":40,"carrier":{"type":"LTL","name":"Estes","image":"15145"},"price":534,"premium":200,"additionalServices":"Protect from freezing","freightClass":"Class 400"},{"id":"13602348","pillar":"industrial-manufacturing","keyword":"compressor","origin":{"city":"EVERETT","state":"WA","country":"USA"},"destination":{"city":"MIAMI","state":"FL","country":"USA"},"value":0,"description":"COMPRESSOR AND FANS","height":42,"itemCondition":"","length":31,"packaging":"Pallet","quantity":1,"weight":540,"width":21,"carrier":{"type":"LTL","name":"Estes","image":"15145"},"price":534,"premium":200,"additionalServices":"Protect from freezing","freightClass":"Class 400"},{"id":"13789380","pillar":"industrial-manufacturing","keyword":"compressor","origin":{"city":"CHICAGO","state":"IL","country":"USA"},"destination":{"city":"CORDOVA","state":"TN","country":"USA"},"value":0,"description":"30 Gallon Air Compressor","height":48,"itemCondition":"","length":48,"packaging":"Tanks","quantity":1,"weight":200,"width":48,"carrier":{"type":"LTL","name":"Estes","image":"15145"},"price":534,"premium":200,"additionalServices":"Protect from freezing","freightClass":"Class 400"},{"id":"13839176","pillar":"industrial-manufacturing","keyword":"compressor","origin":{"city":"FUQUAY VARINA","state":"NC","country":"USA"},"destination":{"city":"SUGAR LAND","state":"TX","country":"USA"},"value":1200,"description":"Used Air Techniques AirStar 30-Dual Head OilLess Dental Air Compressor Bolted to Pallet/plastic wrap","height":37,"itemCondition":"Used","length":48,"packaging":"Pallet","quantity":1,"weight":280,"width":36,"carrier":{"type":"LTL","name":"Estes","image":"15145"},"price":534,"premium":200,"additionalServices":"Protect from freezing","freightClass":"Class 400"},{"id":"13928908","pillar":"industrial-manufacturing","keyword":"compressor","origin":{"city":"CHESNEE","state":"SC","country":"USA"},"destination":{"city":"PHARR","state":"TX","country":"USA"},"value":550,"description":"Copeland compressor","height":28,"itemCondition":"New","length":40,"packaging":"Pallet","quantity":1,"weight":185,"width":40,"carrier":{"type":"LTL","name":"Estes","image":"15145"},"price":534,"premium":200,"additionalServices":"Protect from freezing","freightClass":"Class 400"},{"id":"13954804","pillar":"industrial-manufacturing","keyword":"compressor","origin":{"city":"MASPETH","state":"NY","country":"USA"},"destination":{"city":"WELLINGTON","state":"FL","country":"USA"},"value":0,"description":"Compressor","height":72,"itemCondition":"\tNew","length":48,"packaging":"Pallet","quantity":1,"weight":450,"width":48,"carrier":{"type":"LTL","name":"Estes","image":"15145"},"price":534,"premium":200,"additionalServices":"Protect from freezing","freightClass":"Class 400"},{"id":"13978208","pillar":"industrial-manufacturing","keyword":"compressor","origin":{"city":"AUSTIN","state":"TX","country":"USA"},"destination":{"city":"LEES SUMMIT","state":"MO","country":"USA"},"value":300,"description":"Air compressor","height":60,"itemCondition":"Used","length":48,"packaging":"Pallet","quantity":1,"weight":207,"width":40,"carrier":{"type":"LTL","name":"Estes","image":"15145"},"price":534,"premium":200,"additionalServices":"Protect from freezing","freightClass":"Class 400"},{"id":"13980846","pillar":"industrial-manufacturing","keyword":"compressor","origin":{"city":"AUBURN","state":"WA","country":"USA"},"destination":{"city":"BELLE PLAINE","state":"KS","country":"USA"},"value":5000,"description":"SKID WITH AIRCOMPRESSOR","height":48,"itemCondition":"Used","length":60,"packaging":"Skids","quantity":1,"weight":1600,"width":40,"carrier":{"type":"LTL","name":"Estes","image":"15145"},"price":534,"premium":200,"additionalServices":"Protect from freezing","freightClass":"Class 400"},{"id":"13989770","pillar":"industrial-manufacturing","keyword":"compressor","origin":{"city":"EVANS","state":"GA","country":"USA"},"destination":{"city":"COLUMBUS","state":"TX","country":"USA"},"value":500,"description":"Small Air compressor","height":21,"itemCondition":"Used","length":40,"packaging":"Boxes","quantity":1,"weight":160,"width":20,"carrier":{"type":"LTL","name":"Estes","image":"15145"},"price":534,"premium":200,"additionalServices":"Protect from freezing","freightClass":"Class 400"},{"id":"14035352","pillar":"industrial-manufacturing","keyword":"compressor","origin":{"city":"GLUCKSTADT","state":"MS","country":"USA"},"destination":{"city":"BILOXI","state":"MS","country":"USA"},"value":800,"description":"compressor","height":32,"itemCondition":"New","length":24,"packaging":"Pallet","quantity":1,"weight":100,"width":24,"carrier":{"type":"LTL","name":"Estes","image":"15145"},"price":534,"premium":200,"additionalServices":"Protect from freezing","freightClass":"Class 400"},{"id":"14100574","pillar":"industrial-manufacturing","keyword":"compressor","origin":{"city":"HUDSON","state":"FL","country":"USA"},"destination":{"city":"WALLIS","state":"TX","country":"USA"},"value":1100,"description":"air compressor on pallet","height":18,"itemCondition":"Used","length":36,"packaging":"Pallet","quantity":1,"weight":220,"width":24,"carrier":{"type":"LTL","name":"Estes","image":"15145"},"price":534,"premium":200,"additionalServices":"Protect from freezing","freightClass":"Class 400"},{"id":"14145324","pillar":"industrial-manufacturing","keyword":"compressor","origin":{"city":"EL MONTE","state":"CA","country":"USA"},"destination":{"city":"SAN ANTONIO","state":"TX","country":"USA"},"value":0,"description":"compressor","height":27,"itemCondition":"New","length":40,"packaging":"Pallet","quantity":1,"weight":125,"width":22,"carrier":{"type":"LTL","name":"Estes","image":"15145"},"price":534,"premium":200,"additionalServices":"Protect from freezing","freightClass":"Class 400"},{"id":"14158394","pillar":"industrial-manufacturing","keyword":"compressor","origin":{"city":"GARDNER","state":"MA","country":"USA"},"destination":{"city":"HIALEAH","state":"FL","country":"USA"},"value":4811,"description":"Air Compressor","height":60,"itemCondition":"Used","length":86,"packaging":"Pallet","quantity":1,"weight":2800,"width":62,"carrier":{"type":"LTL","name":"Estes","image":"15145"},"price":534,"premium":200,"additionalServices":"Protect from freezing","freightClass":"Class 400"},{"id":"14174692","pillar":"industrial-manufacturing","keyword":"compressor","origin":{"city":"MILBANK","state":"SD","country":"USA"},"destination":{"city":"MIDDLETOWN","state":"OH","country":"USA"},"value":2800,"description":"POWEREX COMPRESSOR AND AIR DRYER","height":55,"itemCondition":"Used","length":60,"packaging":"Pallet","quantity":1,"weight":450,"width":40,"carrier":{"type":"LTL","name":"Estes","image":"15145"},"price":534,"premium":200,"additionalServices":"Protect from freezing","freightClass":"Class 400"},{"id":"14181868","pillar":"industrial-manufacturing","keyword":"compressor","origin":{"city":"BELLEVUE","state":"IA","country":"USA"},"destination":{"city":"PADUCAH","state":"KY","country":"USA"},"value":1,"description":"Cast Iron Refrigeration Compressor","height":24,"itemCondition":"New","length":25,"packaging":"Boxes","quantity":1,"weight":235,"width":22,"carrier":{"type":"LTL","name":"Estes","image":"15145"},"price":534,"premium":200,"additionalServices":"Protect from freezing","freightClass":"Class 400"},{"id":"14199596","pillar":"industrial-manufacturing","keyword":"compressor","origin":{"city":"PINELLAS PARK","state":"FL","country":"USA"},"destination":{"city":"MIAMI","state":"FL","country":"USA"},"value":1200,"description":"Air conditioning compressor","height":21,"itemCondition":"Used","length":33,"packaging":"Pallet","quantity":1,"weight":415,"width":26,"carrier":{"type":"LTL","name":"Estes","image":"15145"},"price":534,"premium":200,"additionalServices":"Protect from freezing","freightClass":"Class 400"},{"id":"14229326","pillar":"industrial-manufacturing","keyword":"compressor","origin":{"city":"DALLAS","state":"TX","country":"USA"},"destination":{"city":"BATON ROUGE","state":"LA","country":"USA"},"value":0,"description":"compressor","height":22,"itemCondition":"New","length":47,"packaging":"Pallet","quantity":1,"weight":97,"width":22,"carrier":{"type":"LTL","name":"Estes","image":"15145"},"price":534,"premium":200,"additionalServices":"Protect from freezing","freightClass":"Class 400"},{"id":"14241646","pillar":"industrial-manufacturing","keyword":"compressor","origin":{"city":"DIDSBURY","state":"AB","country":"CAN"},"destination":{"city":"ROSEBURG","state":"OR","country":"USA"},"value":500,"description":"Compressor","height":40,"itemCondition":"Used","length":48,"packaging":"Pallet","quantity":1,"weight":800,"width":40,"carrier":{"type":"LTL","name":"Estes","image":"15145"},"price":534,"premium":200,"additionalServices":"Protect from freezing","freightClass":"Class 400"},{"id":"14254930","pillar":"industrial-manufacturing","keyword":"compressor","origin":{"city":"ASHBY","state":"MN","country":"USA"},"destination":{"city":"TACOMA","state":"WA","country":"USA"},"value":500,"description":"Compressor Core","height":28,"itemCondition":"New","length":48,"packaging":"Pallet","quantity":1,"weight":331,"width":40,"carrier":{"type":"LTL","name":"Estes","image":"15145"},"price":534,"premium":200,"additionalServices":"Protect from freezing","freightClass":"Class 400"},{"id":"14275984","pillar":"industrial-manufacturing","keyword":"compressor","origin":{"city":"PALM DESERT","state":"CA","country":"USA"},"destination":{"city":"OAKLAND","state":"CA","country":"USA"},"value":1000,"description":"Gas Compressor","height":54,"itemCondition":"Used","length":48,"packaging":"Pallet","quantity":1,"weight":545,"width":48,"carrier":{"type":"LTL","name":"Estes","image":"15145"},"price":534,"premium":200,"additionalServices":"Protect from freezing","freightClass":"Class 400"},{"id":"14280500","pillar":"industrial-manufacturing","keyword":"compressor","origin":{"city":"PALM DESERT","state":"CA","country":"USA"},"destination":{"city":"BEGGS","state":"OK","country":"USA"},"value":1000,"description":"Gas Compressor","height":54,"itemCondition":"Used","length":48,"packaging":"Pallet","quantity":1,"weight":545,"width":48,"carrier":{"type":"LTL","name":"Estes","image":"15145"},"price":534,"premium":200,"additionalServices":"Protect from freezing","freightClass":"Class 400"},{"id":"14302104","pillar":"industrial-manufacturing","keyword":"compressor","origin":{"city":"HAVELOCK","state":"NC","country":"USA"},"destination":{"city":"HIALEAH","state":"FL","country":"USA"},"value":5000,"description":"2 compressors boxed on pallet","height":28,"itemCondition":"New","length":52,"packaging":"Pallet","quantity":2,"weight":430,"width":44,"carrier":{"type":"LTL","name":"Estes","image":"15145"},"price":534,"premium":200,"additionalServices":"Protect from freezing","freightClass":"Class 400"},{"id":"14328584","pillar":"industrial-manufacturing","keyword":"compressor","origin":{"city":"CHARLOTTE","state":"NC","country":"USA"},"destination":{"city":"WEST BOYLSTON","state":"MA","country":"USA"},"value":5000,"description":"2014 Kaeser M57 Air Compressor, S/N 1319","height":49,"itemCondition":"Used","length":85,"packaging":"Crates","quantity":1,"weight":1905,"width":34,"carrier":{"type":"LTL","name":"Estes","image":"15145"},"price":534,"premium":200,"additionalServices":"Protect from freezing","freightClass":"Class 400"}]