[{"id":"13761848","pillar":"e-commerce","keyword":"ecommerce shipping","origin":{"date":"11/9/18","city":"OLATHE","state":"KS","country":"USA"},"destination":{"date":"11/13/18","city":"RUSHFORD","state":"MN","country":"USA"},"value":0,"description":"box","height":60,"itemCondition":"","length":48,"packaging":"Pallet","quantity":1,"weight":500,"width":40,"carrier":{"type":"LTL","name":"Estes","image":"15145"},"price":156.17,"premium":200,"additionalServices":"Protect from freezing","freightClass":""},{"id":"13766990","pillar":"e-commerce","keyword":"ecommerce shipping","origin":{"date":"11/19/18","city":"CHARLOTTE","state":"NC","country":"USA"},"destination":{"date":"11/26/18","city":"OLATHE","state":"KS","country":"USA"},"value":0,"description":"BOXES","height":60,"itemCondition":"","length":48,"packaging":"Pallet","quantity":2,"weight":600,"width":40,"carrier":{"type":"LTL","name":"Estes","image":"15145"},"price":396.84,"premium":200,"additionalServices":"Protect from freezing","freightClass":""},{"id":"13866862","pillar":"e-commerce","keyword":"ecommerce shipping","origin":{"date":"4/29/19","city":"SIMI VALLEY","state":"CA","country":"USA"},"destination":{"date":"5/14/19","city":"NORTH JAVA","state":"NY","country":"USA"},"value":7600,"description":"Toys in cardboard boxes","height":71,"itemCondition":"New","length":48,"packaging":"Pallet","quantity":1,"weight":434,"width":40,"carrier":{"type":"LTL","name":"Estes","image":"15145"},"price":258.85,"premium":200,"additionalServices":"Protect from freezing","freightClass":""}]